dahua/cgi_bin.py
dahua/client.py
dahua/exceptions.py
dahua/util.py
dahua/rpc/__init__.py
dahua/rpc/_global.py
dahua/rpc/console.py
dahua/rpc/magic_box.py
dahua/rpc/upgrader.py
dahua/rpc/user_manager.py
dahua/utils/cve.py
dahua/utils/logger.py
dahua/utils/upgrade.py
dahua_rpc_api-0.1.5.dist-info/licenses/LICENSE
dahua_rpc_api-0.1.5.dist-info/METADATA
dahua_rpc_api-0.1.5.dist-info/WHEEL
dahua_rpc_api-0.1.5.dist-info/top_level.txt
dahua_rpc_api-0.1.5.dist-info/RECORD
