Metadata-Version: 2.4
Name: dahua-rpc-api
Version: 0.1.5
Summary: A Python package for interacting with the Dahua RPC API.
Author-email: Sam Redmond <samredmondtech@gmail.com>
License: MIT
Classifier: Programming Language :: Python :: 3
Classifier: License :: OSI Approved :: MIT License
Classifier: Operating System :: OS Independent
Requires-Python: >=3.7
License-File: LICENSE
Requires-Dist: requests>=2.32.3
Dynamic: license-file
